clean_milvus_helm/__init__.py
clean_milvus_helm/main.py
clean_milvus_helm-0.14.dist-info/METADATA
clean_milvus_helm-0.14.dist-info/WHEEL
clean_milvus_helm-0.14.dist-info/entry_points.txt
clean_milvus_helm-0.14.dist-info/RECORD
