Metadata-Version: 2.4
Name: clean-milvus-helm
Version: 0.14
Summary: A tool to clean up old Helm releases
Author-email: Your Name <your.email@example.com>
License: MIT
Requires-Python: >=3.7
Requires-Dist: argparse>=1.4.0
